invenio_rdm_records/__init__.py
invenio_rdm_records/cli.py
invenio_rdm_records/config.py
invenio_rdm_records/ext.py
invenio_rdm_records/oai.py
invenio_rdm_records/proxies.py
invenio_rdm_records/utils.py
invenio_rdm_records/views.py
invenio_rdm_records/webpack.py
invenio_rdm_records/access_requests_ui/__init__.py
invenio_rdm_records/access_requests_ui/views.py
invenio_rdm_records/administration/__init__.py
invenio_rdm_records/administration/views/__init__.py
invenio_rdm_records/administration/views/oai.py
invenio_rdm_records/alembic/0cf260eb8e97_create_table_for_secret_links.py
invenio_rdm_records/alembic/1746626978_drop_rdmrecordquota_user_id_unique_.py
invenio_rdm_records/alembic/2186256e8d9b_add_deletion_status_to_rdmrecords.py
invenio_rdm_records/alembic/4a15e8671f4d_create_rdm_records_tables.py
invenio_rdm_records/alembic/88d1463de5c0_create_parent_record_table.py
invenio_rdm_records/alembic/8ed1a438601c_migrate_secret_links.py
invenio_rdm_records/alembic/9e0ac518b9df_create_records_communities_m2m_table.py
invenio_rdm_records/alembic/__init__.py
invenio_rdm_records/alembic/a2a6819f14f1_create_files_and_media_files_versioning_.py
invenio_rdm_records/alembic/a3957490361d_remove_pidrelations_tables.py
invenio_rdm_records/alembic/a6bfa06b1a6d_add_origin_and_description_to_secret_links.py
invenio_rdm_records/alembic/b822ba22c688_create_rdm_records_branch.py
invenio_rdm_records/alembic/cfcb8cb78708_create_access_request_tokens_table.py
invenio_rdm_records/alembic/faf0cefa79a0_create_record_quota_tables.py
invenio_rdm_records/alembic/ff860d48fb4b_create_media_files_table.py
invenio_rdm_records/alembic/ff9bec971d30_add_indexes.py
invenio_rdm_records/alembic/ffd725001655_add_field_to_record_consent_to_share_.py
invenio_rdm_records/assets/semantic-ui/js/invenio_rdm_records/.eslintrc.yml
invenio_rdm_records/assets/semantic-ui/js/invenio_rdm_records/.prettierrc
invenio_rdm_records/assets/semantic-ui/js/invenio_rdm_records/index.js
invenio_rdm_records-23.1.1.dist-info/licenses/AUTHORS.rst
invenio_rdm_records-23.1.1.dist-info/licenses/LICENSE
invenio_rdm_records-23.1.1.dist-info/METADATA
invenio_rdm_records-23.1.1.dist-info/WHEEL
invenio_rdm_records-23.1.1.dist-info/entry_points.txt
invenio_rdm_records-23.1.1.dist-info/top_level.txt
invenio_rdm_records-23.1.1.dist-info/RECORD
