Metadata-Version: 2.4
Name: invenio-rdm-records
Version: 23.1.1
Summary: InvenioRDM module for the communities feature.
Home-page: https://github.com/inveniosoftware/invenio-rdm-records
Author: CERN
Author-email: info@inveniosoftware.org
License: MIT
Keywords: invenio rdm data model
Platform: any
Classifier: Development Status :: 5 - Production/Stable
Requires-Python: >=3.7
License-File: LICENSE
License-File: AUTHORS.rst
Requires-Dist: arrow>=0.17.0
Requires-Dist: babel-edtf>=1.2.0
Requires-Dist: citeproc-py-styles<1.0.0,>=0.1.2
Requires-Dist: citeproc-py>=0.6.0
Requires-Dist: commonmeta-py<0.182,>=0.8.4
Requires-Dist: datacite<2.0.0,>=1.1.1
Requires-Dist: dcxml<1.0.0,>=0.1.2
Requires-Dist: Faker>=2.0.3
Requires-Dist: flask-iiif<2.0.0,>=1.0.0
Requires-Dist: invenio-administration<5.0.0,>=4.0.0
Requires-Dist: invenio-base<3.0.0,>=2.3.0
Requires-Dist: invenio-checks<4.0.0,>=3.0.0
Requires-Dist: invenio-communities<23.0.0,>=22.0.0
Requires-Dist: invenio-drafts-resources<8.0.0,>=7.0.0
Requires-Dist: invenio-records-resources<9.0.0,>=8.0.0
Requires-Dist: invenio-github<5.0.0,>=4.0.0
Requires-Dist: invenio-i18n<4.0.0,>=3.0.0
Requires-Dist: invenio-jobs<7.0.0,>=6.0.0
Requires-Dist: invenio-oaiserver<4.0.0,>=3.0.0
Requires-Dist: invenio-oauth2server<4.0.0,>=3.0.0
Requires-Dist: invenio-stats<6.0.0,>=5.0.0
Requires-Dist: invenio-vocabularies<10.0.0,>=9.0.0
Requires-Dist: nameparser>=1.1.1
Requires-Dist: pycountry>=22.3.5
Requires-Dist: pydash<7.0.0,>=6.0.0
Requires-Dist: pytz>=2020.4
Requires-Dist: pyyaml>=5.4.0
Requires-Dist: python-slugify>=8.0.1
Provides-Extra: tests
Requires-Dist: pytest-black-ng>=0.4.0; extra == "tests"
Requires-Dist: invenio-app<3.0.0,>=2.1.0; extra == "tests"
Requires-Dist: invenio-db[mysql,postgresql]<3.0.0,>=2.0.0; extra == "tests"
Requires-Dist: pytest-invenio<4.0.0,>=3.0.0; extra == "tests"
Requires-Dist: pytest-mock>=1.6.0; extra == "tests"
Requires-Dist: sphinx>=4.5.0; extra == "tests"
Requires-Dist: tripoli>=2.0.0; extra == "tests"
Provides-Extra: elasticsearch7
Requires-Dist: invenio-search[elasticsearch7]<4.0.0,>=3.0.0; extra == "elasticsearch7"
Provides-Extra: opensearch1
Requires-Dist: invenio-search[opensearch1]<4.0.0,>=3.0.0; extra == "opensearch1"
Provides-Extra: opensearch2
Requires-Dist: invenio-search[opensearch2]<4.0.0,>=3.0.0; extra == "opensearch2"
Dynamic: license-file
